scraper1830/__init__.py
scraper1830/scraper1830.py
scraper1830/scraper_cli.py
scraper1830-0.0.3.dist-info/LICENSE
scraper1830-0.0.3.dist-info/METADATA
scraper1830-0.0.3.dist-info/WHEEL
scraper1830-0.0.3.dist-info/entry_points.txt
scraper1830-0.0.3.dist-info/top_level.txt
scraper1830-0.0.3.dist-info/RECORD
