Metadata-Version: 2.1
Name: scraper1830
Version: 0.0.3
Summary: The goal of this repository is to build a package to scrape game data for 1830 games from the 18xx.games api.
Home-page: https://github.com/siddharthnvenkatesh/1830-game-log-scraper
Author: Siddharth Venkatesh
Author-email: siddharth.n.venkatesh@gmail.com
License: MIT
Project-URL: Bug Tracker, https://github.com/siddharthnvenkatesh/1830-game-log-scraper/issues
Keywords: html/json scraper,board game analysis
Platform: any
Classifier: Development Status :: 3 - Alpha
Classifier: Intended Audience :: Developers
Classifier: License :: OSI Approved :: MIT License
Classifier: Operating System :: OS Independent
Classifier: Programming Language :: Python
Classifier: Programming Language :: Python :: 3.4
Classifier: Programming Language :: Python :: 3.5
Classifier: Programming Language :: Python :: 3.6
Classifier: Programming Language :: Python :: 3.7
Classifier: Programming Language :: Python :: 3.8
Classifier: Topic :: Software Development :: Libraries :: Python Modules
Requires-Python: !=3.0.*,!=3.1.*,!=3.2.*,>=2.7
License-File: LICENSE
Requires-Dist: requests
Requires-Dist: selenium
Requires-Dist: bs4
Requires-Dist: pandas
Requires-Dist: matplotlib
Requires-Dist: seaborn
Requires-Dist: click
Requires-Dist: lxml
